{
  "novelWriter.tagsIndex": {},
  "novelWriter.itemIndex": {
    "785085c761654": {
      "headings": {
        "T0001": {"level": "H1", "title": "\u6d2a\u8352\u4ee3\u7801\u67b6\u6784\u5e08", "line": 7, "tag": "", "cCount": 28, "wCount": 5, "pCount": 2, "synopsis": ""}
      }
    },
    "528f8233c37cb": {
      "headings": {
        "T0001": {"level": "H3", "title": "\u5f15\u5b50 \u795e\u8bdd\u7eaa\u5143\u7684\u53ec\u5524", "line": 1, "tag": "", "cCount": 490, "wCount": 29, "pCount": 23, "synopsis": ""}
      }
    },
    "5d0ff8e47d0c1": {
      "headings": {
        "T0001": {"level": "H3", "title": "\u7b2c1\u7ae0\uff1a0\u548c1\u7684\u67b7\u9501\uff0c\u6843\u82b1\u9999\u7684\u60b8\u52a8", "line": 1, "tag": "", "cCount": 1819, "wCount": 51, "pCount": 17, "synopsis": ""}
      }
    },
    "0473edfa83de0": {
      "headings": {
        "T0001": {"level": "H2", "title": "\u65b0\u7ae0\u8282", "line": 1, "tag": "", "cCount": 5321, "wCount": 136, "pCount": 17, "synopsis": ""}
      }
    },
    "77d4cd2ace0b6": {
      "headings": {
        "T0001": {"level": "H3", "title": "\u7b2c\u4e00\u6b21\u7684\u76f8\u9047", "line": 1, "tag": "", "cCount": 6, "wCount": 1, "pCount": 0, "synopsis": ""}
      }
    },
    "efcb6725f9a68": {
      "headings": {
        "T0001": {"level": "H1", "title": "\u897f\u6e38\u4f17\u795e", "line": 1, "tag": "", "cCount": 4, "wCount": 1, "pCount": 0, "synopsis": ""},
        "T0002": {"level": "H3", "title": "\u5929\u5ead\u7684\u67b6\u6784", "line": 3, "tag": "", "cCount": 649, "wCount": 11, "pCount": 5, "synopsis": ""}
      }
    },
    "d96a1ebf50b30": {
      "headings": {
        "T0001": {"level": "H1", "title": "\u5ba0\u7269\u5929\u56e2", "line": 1, "tag": "", "cCount": 4, "wCount": 1, "pCount": 0, "synopsis": ""}
      }
    },
    "46a1803310578": {
      "headings": {
        "T0000": {"level": "H0", "title": "", "line": 0, "tag": "", "cCount": 0, "wCount": 0, "pCount": 0, "synopsis": ""}
      }
    },
    "3ff3a0ce02ec4": {
      "headings": {
        "T0001": {"level": "H2", "title": "\u7b2c\u4e8c\u7ae0 \u91d1\u8272\u8725\u8734\u7684\u4fe1\u4f7f", "line": 1, "tag": "", "cCount": 1424, "wCount": 38, "pCount": 24, "synopsis": ""}
      }
    },
    "08bb43c25847b": {
      "headings": {
        "T0001": {"level": "H2", "title": "\u7b2c\u4e00\u7ae0 0\u548c1\u7684\u67b7\u9501\uff0c\u6843\u82b1\u9999\u7684\u60b8\u52a8", "line": 1, "tag": "", "cCount": 1573, "wCount": 41, "pCount": 20, "synopsis": ""}
      }
    },
    "7e38fb87d5690": {
      "headings": {
        "T0001": {"level": "H2", "title": "\u5f15\u5b50 \u795e\u8bdd\u7eaa\u5143\u7684\u53ec\u5524", "line": 1, "tag": "", "cCount": 481, "wCount": 27, "pCount": 21, "synopsis": ""}
      }
    },
    "49c13972fa24a": {
      "headings": {
        "T0001": {"level": "H2", "title": "\u7b2c\u4e09\u7ae0 \u91d1\u7b8d\u5fae\u52a8\u7834\u6a0a\u7b3c", "line": 1, "tag": "", "cCount": 1516, "wCount": 48, "pCount": 27, "synopsis": ""}
      }
    },
    "4c1472eda097d": {
      "headings": {
        "T0001": {"level": "H2", "title": "\u7b2c\u56db\u7ae0 \u771f\u8a00\u7591\u4e91\uff0c\u9f9f\u58f3\u85cf\u8e2a", "line": 1, "tag": "", "cCount": 1684, "wCount": 30, "pCount": 25, "synopsis": ""}
      }
    },
    "409a9545104e6": {
      "headings": {
        "T0001": {"level": "H2", "title": "\u7b2c\u4e94\u7ae0 \u9006\u5492\u7792\u5929\uff0c\u571f\u62e8\u66ff\u8eab", "line": 1, "tag": "", "cCount": 1725, "wCount": 39, "pCount": 26, "synopsis": ""}
      }
    },
    "9905738714b16": {
      "headings": {
        "T0000": {"level": "H0", "title": "", "line": 0, "tag": "", "cCount": 764, "wCount": 36, "pCount": 3, "synopsis": ""}
      }
    },
    "6243431507fde": {
      "headings": {
        "T0001": {"level": "H2", "title": "\u7b2c\u4e03\u7ae0 \u6d1e\u5f00\u89c1\u6545\u4eba \u6b22\u8bed\u6ee1\u6d1e\u5929", "line": 1, "tag": "", "cCount": 1212, "wCount": 27, "pCount": 21, "synopsis": ""}
      }
    },
    "16d81e68a0249": {
      "headings": {
        "T0000": {"level": "H0", "title": "", "line": 0, "tag": "", "cCount": 829, "wCount": 18, "pCount": 1, "synopsis": ""}
      }
    },
    "5026bd8ff2484": {
      "headings": {
        "T0001": {"level": "H2", "title": "\u7b2c\u5341\u7ae0\uff08\u4e0a\uff09 \u7bdd\u706b\u8bae\u4e8b\u30fb\u82b1\u679c\u5c71\u6838\u5fc3\u73ed\u5b50\u5c31\u4f4d", "line": 1, "tag": "", "cCount": 2521, "wCount": 39, "pCount": 22, "synopsis": ""}
      }
    },
    "496fa250009ce": {
      "headings": {
        "T0001": {"level": "H2", "title": "\u7b2c\u5341\u7ae0\uff08\u4e0b\uff09 \u84dd\u56fe\u521d\u73b0\u30fb\u6708\u4e0b\u7ea6\u5b9a", "line": 1, "tag": "", "cCount": 4101, "wCount": 46, "pCount": 37, "synopsis": ""}
      }
    },
    "e332f87dfb01a": {
      "headings": {
        "T0000": {"level": "H0", "title": "", "line": 0, "tag": "", "cCount": 1640, "wCount": 49, "pCount": 14, "synopsis": ""}
      }
    },
    "035c8b5ca5b10": {
      "headings": {
        "T0000": {"level": "H0", "title": "", "line": 0, "tag": "", "cCount": 0, "wCount": 0, "pCount": 0, "synopsis": ""}
      }
    },
    "15f42db1e9537": {
      "headings": {
        "T0000": {"level": "H0", "title": "", "line": 0, "tag": "", "cCount": 0, "wCount": 0, "pCount": 0, "synopsis": ""}
      }
    },
    "91dd8cc7a7c6c": {
      "headings": {
        "T0000": {"level": "H0", "title": "", "line": 0, "tag": "", "cCount": 0, "wCount": 0, "pCount": 0, "synopsis": ""}
      }
    },
    "a5cb3a3d44724": {
      "headings": {
        "T0001": {"level": "H2", "title": "\u7b2c\u516d\u7ae0 \u5f52\u5c71\u30fb\u8352\u6797\u91cc\u7684\u4e8c\u8fdb\u5236\u7eb9\u8def", "line": 1, "tag": "", "cCount": 1428, "wCount": 41, "pCount": 33, "synopsis": ""}
      }
    },
    "84fe2d9d78b92": {
      "headings": {
        "T0001": {"level": "H2", "title": "\u7b2c\u516b\u7ae0 \u591c\u8bdd\u30fb\u87e0\u6843\u6838\u91cc\u7684\u65e7\u4ee3\u7801", "line": 1, "tag": "", "cCount": 1111, "wCount": 24, "pCount": 19, "synopsis": ""}
      }
    },
    "38a4ac3e2101f": {
      "headings": {
        "T0001": {"level": "H2", "title": "\u7b2c\u4e5d\u7ae0 \u95ef\u8425\u30fb\u5357\u5929\u95e8\u91cc\u65e7\u76f8\u9022", "line": 1, "tag": "", "cCount": 3091, "wCount": 52, "pCount": 39, "synopsis": ""}
      }
    },
    "bab8bfdd61171": {
      "headings": {
        "T0001": {"level": "H2", "title": "\u7b2c\u4e03\u7ae0 \u6d1e\u5f00\u89c1\u6545\u4eba \u6b22\u8bed\u6ee1\u6d1e\u5929", "line": 1, "tag": "", "cCount": 1608, "wCount": 39, "pCount": 1, "synopsis": ""}
      }
    },
    "a2fd44563a73b": {
      "headings": {
        "T0001": {"level": "H2", "title": "\u5f15\u5b50 \u795e\u8bdd\u7eaa\u5143\u7684\u53ec\u5524", "line": 1, "tag": "", "cCount": 481, "wCount": 27, "pCount": 21, "synopsis": ""},
        "T0002": {"level": "H2", "title": "\u7b2c\u4e00\u7ae0 0\u548c1\u7684\u67b7\u9501\uff0c\u6843\u82b1\u9999\u7684\u60b8\u52a8", "line": 45, "tag": "", "cCount": 1573, "wCount": 41, "pCount": 20, "synopsis": ""},
        "T0003": {"level": "H2", "title": "\u7b2c\u4e8c\u7ae0 \u91d1\u8272\u8725\u8734\u7684\u4fe1\u4f7f", "line": 87, "tag": "", "cCount": 1424, "wCount": 38, "pCount": 24, "synopsis": ""},
        "T0004": {"level": "H2", "title": "\u7b2c\u4e09\u7ae0 \u91d1\u7b8d\u5fae\u52a8\u7834\u6a0a\u7b3c", "line": 139, "tag": "", "cCount": 1516, "wCount": 48, "pCount": 27, "synopsis": ""},
        "T0005": {"level": "H2", "title": "\u7b2c\u56db\u7ae0 \u771f\u8a00\u7591\u4e91\uff0c\u9f9f\u58f3\u85cf\u8e2a", "line": 199, "tag": "", "cCount": 1684, "wCount": 30, "pCount": 25, "synopsis": ""},
        "T0006": {"level": "H2", "title": "\u7b2c\u4e94\u7ae0 \u9006\u5492\u7792\u5929\uff0c\u571f\u62e8\u66ff\u8eab", "line": 251, "tag": "", "cCount": 1725, "wCount": 39, "pCount": 26, "synopsis": ""},
        "T0007": {"level": "H2", "title": "\u7b2c\u516d\u7ae0 \u5f52\u5c71\u30fb\u8352\u6797\u91cc\u7684\u4e8c\u8fdb\u5236\u7eb9\u8def", "line": 307, "tag": "", "cCount": 1428, "wCount": 41, "pCount": 33, "synopsis": ""},
        "T0008": {"level": "H2", "title": "\u7b2c\u4e03\u7ae0 \u6d1e\u5f00\u89c1\u6545\u4eba \u6b22\u8bed\u6ee1\u6d1e\u5929", "line": 378, "tag": "", "cCount": 1212, "wCount": 27, "pCount": 21, "synopsis": ""},
        "T0009": {"level": "H2", "title": "\u7b2c\u516b\u7ae0 \u591c\u8bdd\u30fb\u87e0\u6843\u6838\u91cc\u7684\u65e7\u4ee3\u7801", "line": 422, "tag": "", "cCount": 1111, "wCount": 24, "pCount": 19, "synopsis": ""},
        "T0010": {"level": "H2", "title": "\u7b2c\u4e5d\u7ae0 \u95ef\u8425\u30fb\u5357\u5929\u95e8\u91cc\u65e7\u76f8\u9022", "line": 461, "tag": "", "cCount": 3091, "wCount": 52, "pCount": 39, "synopsis": ""},
        "T0011": {"level": "H2", "title": "\u7b2c\u5341\u7ae0\uff08\u4e0a\uff09 \u7bdd\u706b\u8bae\u4e8b\u30fb\u82b1\u679c\u5c71\u6838\u5fc3\u73ed\u5b50\u5c31\u4f4d", "line": 544, "tag": "", "cCount": 2519, "wCount": 39, "pCount": 22, "synopsis": ""},
        "T0012": {"level": "H2", "title": "\u7b2c\u5341\u7ae0\uff08\u4e0b\uff09 \u84dd\u56fe\u521d\u73b0\u30fb\u6708\u4e0b\u7ea6\u5b9a", "line": 589, "tag": "", "cCount": 4102, "wCount": 46, "pCount": 37, "synopsis": ""},
        "T0013": {"level": "H2", "title": "\u7b2c\u5341\u4e00\u7ae0 \u6674\u5149\u7834\u6653\u30fb\u5de1\u5c71\u542f\u9014", "line": 666, "tag": "", "cCount": 3318, "wCount": 46, "pCount": 32, "synopsis": ""},
        "T0014": {"level": "H2", "title": "\u7b2c\u5341\u4e8c\u7ae0 \u7b2c\u4e00\u65e5 \u6ca7\u6e9f\u5fc6\u65e7\u30fb\u77f3\u7554\u6f6e\u58f0\uff08\u65e5\u7bc7\uff09", "line": 733, "tag": "", "cCount": 3566, "wCount": 46, "pCount": 35, "synopsis": ""},
        "T0015": {"level": "H2", "title": "\u7b2c\u5341\u4e09\u7ae0 \u7b2c\u4e00\u65e5 \u706f\u4e0b\u65e7\u75d5\u00b7\u65e5\u5fd7\u8c1c\u7ae0\uff08\u591c\u7bc7\uff09", "line": 805, "tag": "", "cCount": 3676, "wCount": 124, "pCount": 53, "synopsis": ""},
        "T0016": {"level": "H2", "title": "\u7b2c\u5341\u56db\u7ae0 \u7b2c\u4e8c\u65e5 \u6668\u9732\u6cbe\u8863\u00b7\u57fa\u5efa\u592f\u571f\uff08\u65e5\u7bc7\uff09", "line": 913, "tag": "", "cCount": 3135, "wCount": 94, "pCount": 36, "synopsis": ""},
        "T0017": {"level": "H2", "title": "\u7b2c\u5341\u4e94\u7ae0 \u7b2c\u4e8c\u65e5 \u661f\u5782\u5e73\u91ce\u00b7\u6843\u4e0b\u79c1\u8bed\uff08\u591c\u7bc7\uff09", "line": 988, "tag": "", "cCount": 2869, "wCount": 55, "pCount": 38, "synopsis": ""}
      }
    },
    "e1b00210814b9": {
      "headings": {
        "T0000": {"level": "H0", "title": "", "line": 0, "tag": "", "cCount": 0, "wCount": 0, "pCount": 0, "synopsis": ""}
      }
    },
    "71697362c360b": {
      "headings": {
        "T0000": {"level": "H0", "title": "", "line": 0, "tag": "", "cCount": 18706, "wCount": 699, "pCount": 39, "synopsis": ""}
      }
    },
    "0bd40b30b92eb": {
      "headings": {
        "T0000": {"level": "H0", "title": "", "line": 0, "tag": "", "cCount": 652, "wCount": 34, "pCount": 2, "synopsis": ""}
      }
    },
    "a747a1b5b5590": {
      "headings": {
        "T0000": {"level": "H0", "title": "", "line": 0, "tag": "", "cCount": 1104, "wCount": 44, "pCount": 1, "synopsis": ""}
      }
    },
    "af6ff8a93b470": {
      "headings": {
        "T0001": {"level": "H2", "title": "\u7b2c\u5341\u4e00\u7ae0 \u6674\u5149\u7834\u6653\u30fb\u5de1\u5c71\u542f\u9014", "line": 1, "tag": "", "cCount": 2468, "wCount": 47, "pCount": 35, "synopsis": ""}
      }
    },
    "ff4fa2ed6bc30": {
      "headings": {
        "T0001": {"level": "H2", "title": "\u7b2c\u5341\u4e09\u7ae0 \u7b2c\u4e00\u65e5 \u706f\u4e0b\u65e7\u75d5\u00b7\u65e5\u5fd7\u8c1c\u7ae0\uff08\u591c\u7bc7\uff09", "line": 1, "tag": "", "cCount": 3677, "wCount": 124, "pCount": 53, "synopsis": ""}
      }
    },
    "7e4011c4bb28c": {
      "headings": {
        "T0001": {"level": "H2", "title": "\u7b2c\u5341\u4e8c\u7ae0 \u7b2c\u4e00\u65e5 \u6ca7\u6e9f\u5fc6\u65e7\u30fb\u77f3\u7554\u6f6e\u58f0\uff08\u65e5\u7bc7\uff09", "line": 1, "tag": "", "cCount": 3566, "wCount": 46, "pCount": 35, "synopsis": ""}
      }
    },
    "2ac1bec84da0e": {
      "headings": {
        "T0001": {"level": "H2", "title": "\u65b0\u7ae0\u8282", "line": 1, "tag": "", "cCount": 3, "wCount": 1, "pCount": 0, "synopsis": ""}
      }
    },
    "3c9b7eb4a0672": {
      "headings": {
        "T0001": {"level": "H2", "title": "\u7b2c\u5341\u56db\u7ae0 \u7b2c\u4e8c\u65e5 \u6668\u9732\u6cbe\u8863\u00b7\u57fa\u5efa\u592f\u571f\uff08\u65e5\u7bc7\uff09", "line": 1, "tag": "", "cCount": 3136, "wCount": 94, "pCount": 36, "synopsis": ""}
      }
    },
    "d99c0a5984ddf": {
      "headings": {
        "T0001": {"level": "H2", "title": "\u7b2c\u5341\u4e94\u7ae0 \u7b2c\u4e8c\u65e5 \u661f\u5782\u5e73\u91ce\u00b7\u6843\u4e0b\u79c1\u8bed\uff08\u591c\u7bc7\uff09", "line": 1, "tag": "", "cCount": 2869, "wCount": 55, "pCount": 38, "synopsis": ""}
      }
    }
  }
}
